meilisync_config_keygen/__init__.py
meilisync_config_keygen/__main__.py
meilisync_config_keygen/test_suite_analysis/metadata.json
meilisync_config_keygen-0.0.4.dist-info/METADATA
meilisync_config_keygen-0.0.4.dist-info/WHEEL
meilisync_config_keygen-0.0.4.dist-info/licenses/LICENSE
meilisync_config_keygen-0.0.4.dist-info/RECORD
