Metadata-Version: 2.1
Name: meilisync_config_keygen
Version: 0.0.4
Summary: A package designed to generate the Meilisearch API key and implement it in config.yml meilisync service
Project-URL: Homepage, https://github.com/predare/meilisync_config_keygen
Project-URL: Bug Tracker, https://github.com/predare/meilisync_config_keygen/issues
Author-email: predare <predare12000@gmail.com>
License-File: LICENSE
Classifier: License :: OSI Approved :: MIT License
Classifier: Operating System :: OS Independent
Classifier: Programming Language :: Python :: 3
Requires-Python: >=3.7
